rgbnotes/__init__.py
rgbnotes/error.py
rgbnotes/api_resources/__init__.py
rgbnotes/api_resources/account.py
rgbnotes/api_resources/alias.py
rgbnotes/api_resources/asset.py
rgbnotes/api_resources/file.py
rgbnotes/api_resources/note.py
rgbnotes/api_resources/project.py
rgbnotes/api_resources/snapshot.py
rgbnotes/api_resources/token.py
rgbnotes/api_resources/user.py
rgbnotes/api_resources/webhook.py
rgbnotes/api_resources/abstract/__init__.py
rgbnotes/api_resources/abstract/api_resource.py
rgbnotes/api_resources/abstract/createable_api_resource.py
rgbnotes/api_resources/abstract/deletable_api_resource.py
rgbnotes/api_resources/abstract/listable_api_resource.py
rgbnotes/api_resources/abstract/retrievable_api_resource.py
rgbnotes/api_resources/abstract/updateable_api_resource.py
rgbnotes-1.2.11.dist-info/DESCRIPTION.rst
rgbnotes-1.2.11.dist-info/METADATA
rgbnotes-1.2.11.dist-info/RECORD
rgbnotes-1.2.11.dist-info/WHEEL
rgbnotes-1.2.11.dist-info/metadata.json
rgbnotes-1.2.11.dist-info/top_level.txt
