Metadata-Version: 2.0
Name: rgbnotes
Version: 1.2.11
Summary: Python bindings for the RGB Notes API
Home-page: https://github.com/rgbnotes/rgb-python
Author: rgbnotes
Author-email: support@rgbnotes.com
License: MIT
Platform: UNKNOWN
Requires-Dist: requests (>=0.8.8)
